.DS_Store
polarbear/__init__.py
polarbear/entities.py
polarbear/functions.py
polarbear/io.py
polarbear/models.py
polarbear-0.0.0.dev10.dist-info/METADATA
polarbear-0.0.0.dev10.dist-info/WHEEL
polarbear-0.0.0.dev10.dist-info/top_level.txt
polarbear-0.0.0.dev10.dist-info/RECORD
