Metadata-Version: 2.1
Name: polarbear
Version: 0.0.0.dev10
Summary: logic for social science survey data
Home-page: UNKNOWN
Author: UNKNOWN
Author-email: UNKNOWN
License: UNKNOWN
Platform: UNKNOWN
Requires-Dist: pandas
Requires-Dist: savReaderWriter
Requires-Dist: sqlalchemy
Requires-Dist: xlrd
Requires-Dist: openpyxl
